{
  "version": "5",
  "dialect": "mysql",
  "id": "d7bc1104-84c1-427a-8e4d-bf422a53d848",
  "prevId": "8e846bb0-d66d-4817-b33f-df2225581d1e",
  "tables": {
    "app_roles": {
      "name": "app_roles",
      "columns": {
        "id": {
          "name": "id",
          "type": "int",
          "primaryKey": false,
          "notNull": true,
          "autoincrement": true
        },
        "userId": {
          "name": "userId",
          "type": "int",
          "primaryKey": false,
          "notNull": true,
          "autoincrement": false
        },
        "appRole": {
          "name": "appRole",
          "type": "enum('customer','technician','branch_manager','hq_admin')",
          "primaryKey": false,
          "notNull": true,
          "autoincrement": false,
          "default": "'customer'"
        },
        "loginId": {
          "name": "loginId",
          "type": "varchar(64)",
          "primaryKey": false,
          "notNull": false,
          "autoincrement": false
        },
        "passwordHash": {
          "name": "passwordHash",
          "type": "varchar(128)",
          "primaryKey": false,
          "notNull": false,
          "autoincrement": false
        },
        "phoneNumber": {
          "name": "phoneNumber",
          "type": "varchar(20)",
          "primaryKey": false,
          "notNull": false,
          "autoincrement": false
        },
        "name": {
          "name": "name",
          "type": "varchar(50)",
          "primaryKey": false,
          "notNull": false,
          "autoincrement": false
        },
        "branchId": {
          "name": "branchId",
          "type": "int",
          "primaryKey": false,
          "notNull": false,
          "autoincrement": false
        },
        "mustChangePassword": {
          "name": "mustChangePassword",
          "type": "boolean",
          "primaryKey": false,
          "notNull": true,
          "autoincrement": false,
          "default": false
        },
        "isActive": {
          "name": "isActive",
          "type": "boolean",
          "primaryKey": false,
          "notNull": true,
          "autoincrement": false,
          "default": true
        },
        "createdAt": {
          "name": "createdAt",
          "type": "timestamp",
          "primaryKey": false,
          "notNull": true,
          "autoincrement": false,
          "default": "(now())"
        },
        "updatedAt": {
          "name": "updatedAt",
          "type": "timestamp",
          "primaryKey": false,
          "notNull": true,
          "autoincrement": false,
          "onUpdate": true,
          "default": "(now())"
        }
      },
      "indexes": {},
      "foreignKeys": {},
      "compositePrimaryKeys": {
        "app_roles_id": {
          "name": "app_roles_id",
          "columns": [
            "id"
          ]
        }
      },
      "uniqueConstraints": {
        "app_roles_userId_unique": {
          "name": "app_roles_userId_unique",
          "columns": [
            "userId"
          ]
        }
      },
      "checkConstraint": {}
    },
    "app_settings": {
      "name": "app_settings",
      "columns": {
        "id": {
          "name": "id",
          "type": "int",
          "primaryKey": false,
          "notNull": true,
          "autoincrement": true
        },
        "settingKey": {
          "name": "settingKey",
          "type": "varchar(64)",
          "primaryKey": false,
          "notNull": true,
          "autoincrement": false
        },
        "settingValue": {
          "name": "settingValue",
          "type": "text",
          "primaryKey": false,
          "notNull": false,
          "autoincrement": false
        },
        "updatedAt": {
          "name": "updatedAt",
          "type": "timestamp",
          "primaryKey": false,
          "notNull": true,
          "autoincrement": false,
          "onUpdate": true,
          "default": "(now())"
        }
      },
      "indexes": {},
      "foreignKeys": {},
      "compositePrimaryKeys": {
        "app_settings_id": {
          "name": "app_settings_id",
          "columns": [
            "id"
          ]
        }
      },
      "uniqueConstraints": {
        "app_settings_settingKey_unique": {
          "name": "app_settings_settingKey_unique",
          "columns": [
            "settingKey"
          ]
        }
      },
      "checkConstraint": {}
    },
    "branches": {
      "name": "branches",
      "columns": {
        "id": {
          "name": "id",
          "type": "int",
          "primaryKey": false,
          "notNull": true,
          "autoincrement": true
        },
        "name": {
          "name": "name",
          "type": "varchar(100)",
          "primaryKey": false,
          "notNull": true,
          "autoincrement": false
        },
        "code": {
          "name": "code",
          "type": "varchar(20)",
          "primaryKey": false,
          "notNull": true,
          "autoincrement": false
        },
        "region": {
          "name": "region",
          "type": "varchar(100)",
          "primaryKey": false,
          "notNull": true,
          "autoincrement": false
        },
        "managerName": {
          "name": "managerName",
          "type": "varchar(50)",
          "primaryKey": false,
          "notNull": false,
          "autoincrement": false
        },
        "phoneNumber": {
          "name": "phoneNumber",
          "type": "varchar(20)",
          "primaryKey": false,
          "notNull": false,
          "autoincrement": false
        },
        "address": {
          "name": "address",
          "type": "varchar(200)",
          "primaryKey": false,
          "notNull": false,
          "autoincrement": false
        },
        "isActive": {
          "name": "isActive",
          "type": "boolean",
          "primaryKey": false,
          "notNull": true,
          "autoincrement": false,
          "default": true
        },
        "managerUserId": {
          "name": "managerUserId",
          "type": "int",
          "primaryKey": false,
          "notNull": false,
          "autoincrement": false
        },
        "createdAt": {
          "name": "createdAt",
          "type": "timestamp",
          "primaryKey": false,
          "notNull": true,
          "autoincrement": false,
          "default": "(now())"
        },
        "updatedAt": {
          "name": "updatedAt",
          "type": "timestamp",
          "primaryKey": false,
          "notNull": true,
          "autoincrement": false,
          "onUpdate": true,
          "default": "(now())"
        }
      },
      "indexes": {},
      "foreignKeys": {},
      "compositePrimaryKeys": {
        "branches_id": {
          "name": "branches_id",
          "columns": [
            "id"
          ]
        }
      },
      "uniqueConstraints": {
        "branches_code_unique": {
          "name": "branches_code_unique",
          "columns": [
            "code"
          ]
        }
      },
      "checkConstraint": {}
    },
    "flow_rate_logs": {
      "name": "flow_rate_logs",
      "columns": {
        "id": {
          "name": "id",
          "type": "int",
          "primaryKey": false,
          "notNull": true,
          "autoincrement": true
        },
        "sensorId": {
          "name": "sensorId",
          "type": "varchar(64)",
          "primaryKey": false,
          "notNull": true,
          "autoincrement": false
        },
        "branchId": {
          "name": "branchId",
          "type": "int",
          "primaryKey": false,
          "notNull": false,
          "autoincrement": false
        },
        "apartmentName": {
          "name": "apartmentName",
          "type": "varchar(100)",
          "primaryKey": false,
          "notNull": false,
          "autoincrement": false
        },
        "buildingNumber": {
          "name": "buildingNumber",
          "type": "varchar(20)",
          "primaryKey": false,
          "notNull": false,
          "autoincrement": false
        },
        "roomNumber": {
          "name": "roomNumber",
          "type": "varchar(20)",
          "primaryKey": false,
          "notNull": false,
          "autoincrement": false
        },
        "flowRateLpm": {
          "name": "flowRateLpm",
          "type": "decimal(6,2)",
          "primaryKey": false,
          "notNull": true,
          "autoincrement": false
        },
        "supplyPressure": {
          "name": "supplyPressure",
          "type": "decimal(6,3)",
          "primaryKey": false,
          "notNull": false,
          "autoincrement": false
        },
        "returnPressure": {
          "name": "returnPressure",
          "type": "decimal(6,3)",
          "primaryKey": false,
          "notNull": false,
          "autoincrement": false
        },
        "differentialPressure": {
          "name": "differentialPressure",
          "type": "decimal(6,3)",
          "primaryKey": false,
          "notNull": false,
          "autoincrement": false
        },
        "measuredAt": {
          "name": "measuredAt",
          "type": "timestamp",
          "primaryKey": false,
          "notNull": true,
          "autoincrement": false,
          "default": "(now())"
        },
        "status": {
          "name": "status",
          "type": "enum('정상','주의','경고')",
          "primaryKey": false,
          "notNull": true,
          "autoincrement": false,
          "default": "'정상'"
        },
        "source": {
          "name": "source",
          "type": "enum('WEBHOOK','DEMO')",
          "primaryKey": false,
          "notNull": true,
          "autoincrement": false,
          "default": "'WEBHOOK'"
        },
        "createdAt": {
          "name": "createdAt",
          "type": "timestamp",
          "primaryKey": false,
          "notNull": true,
          "autoincrement": false,
          "default": "(now())"
        }
      },
      "indexes": {},
      "foreignKeys": {},
      "compositePrimaryKeys": {
        "flow_rate_logs_id": {
          "name": "flow_rate_logs_id",
          "columns": [
            "id"
          ]
        }
      },
      "uniqueConstraints": {},
      "checkConstraint": {}
    },
    "flow_rate_settings": {
      "name": "flow_rate_settings",
      "columns": {
        "id": {
          "name": "id",
          "type": "int",
          "primaryKey": false,
          "notNull": true,
          "autoincrement": true
        },
        "sensorId": {
          "name": "sensorId",
          "type": "varchar(64)",
          "primaryKey": false,
          "notNull": true,
          "autoincrement": false
        },
        "branchId": {
          "name": "branchId",
          "type": "int",
          "primaryKey": false,
          "notNull": false,
          "autoincrement": false
        },
        "apartmentName": {
          "name": "apartmentName",
          "type": "varchar(100)",
          "primaryKey": false,
          "notNull": true,
          "autoincrement": false
        },
        "buildingNumber": {
          "name": "buildingNumber",
          "type": "varchar(20)",
          "primaryKey": false,
          "notNull": true,
          "autoincrement": false
        },
        "roomNumber": {
          "name": "roomNumber",
          "type": "varchar(20)",
          "primaryKey": false,
          "notNull": true,
          "autoincrement": false
        },
        "baseFlowRateLpm": {
          "name": "baseFlowRateLpm",
          "type": "decimal(6,2)",
          "primaryKey": false,
          "notNull": true,
          "autoincrement": false,
          "default": "'5.50'"
        },
        "warningRangePercent": {
          "name": "warningRangePercent",
          "type": "int",
          "primaryKey": false,
          "notNull": true,
          "autoincrement": false,
          "default": 30
        },
        "cautionRangePercent": {
          "name": "cautionRangePercent",
          "type": "int",
          "primaryKey": false,
          "notNull": true,
          "autoincrement": false,
          "default": 15
        },
        "alertDurationMinutes": {
          "name": "alertDurationMinutes",
          "type": "int",
          "primaryKey": false,
          "notNull": true,
          "autoincrement": false,
          "default": 10
        },
        "lastFlowRateLpm": {
          "name": "lastFlowRateLpm",
          "type": "decimal(6,2)",
          "primaryKey": false,
          "notNull": false,
          "autoincrement": false
        },
        "lastSupplyPressure": {
          "name": "lastSupplyPressure",
          "type": "decimal(6,3)",
          "primaryKey": false,
          "notNull": false,
          "autoincrement": false
        },
        "lastReturnPressure": {
          "name": "lastReturnPressure",
          "type": "decimal(6,3)",
          "primaryKey": false,
          "notNull": false,
          "autoincrement": false
        },
        "lastDifferentialPressure": {
          "name": "lastDifferentialPressure",
          "type": "decimal(6,3)",
          "primaryKey": false,
          "notNull": false,
          "autoincrement": false
        },
        "lastMeasuredAt": {
          "name": "lastMeasuredAt",
          "type": "timestamp",
          "primaryKey": false,
          "notNull": false,
          "autoincrement": false
        },
        "lastStatus": {
          "name": "lastStatus",
          "type": "enum('정상','주의','경고')",
          "primaryKey": false,
          "notNull": false,
          "autoincrement": false,
          "default": "'정상'"
        },
        "alertStartedAt": {
          "name": "alertStartedAt",
          "type": "timestamp",
          "primaryKey": false,
          "notNull": false,
          "autoincrement": false
        },
        "alertSentAt": {
          "name": "alertSentAt",
          "type": "timestamp",
          "primaryKey": false,
          "notNull": false,
          "autoincrement": false
        },
        "customerId": {
          "name": "customerId",
          "type": "varchar(20)",
          "primaryKey": false,
          "notNull": false,
          "autoincrement": false
        },
        "inspectionStatus": {
          "name": "inspectionStatus",
          "type": "enum('미처리','처리중','처리완료')",
          "primaryKey": false,
          "notNull": false,
          "autoincrement": false,
          "default": "'미처리'"
        },
        "inspectionMemo": {
          "name": "inspectionMemo",
          "type": "text",
          "primaryKey": false,
          "notNull": false,
          "autoincrement": false
        },
        "isActive": {
          "name": "isActive",
          "type": "boolean",
          "primaryKey": false,
          "notNull": true,
          "autoincrement": false,
          "default": true
        },
        "createdAt": {
          "name": "createdAt",
          "type": "timestamp",
          "primaryKey": false,
          "notNull": true,
          "autoincrement": false,
          "default": "(now())"
        },
        "updatedAt": {
          "name": "updatedAt",
          "type": "timestamp",
          "primaryKey": false,
          "notNull": true,
          "autoincrement": false,
          "onUpdate": true,
          "default": "(now())"
        }
      },
      "indexes": {},
      "foreignKeys": {},
      "compositePrimaryKeys": {
        "flow_rate_settings_id": {
          "name": "flow_rate_settings_id",
          "columns": [
            "id"
          ]
        }
      },
      "uniqueConstraints": {
        "flow_rate_settings_sensorId_unique": {
          "name": "flow_rate_settings_sensorId_unique",
          "columns": [
            "sensorId"
          ]
        }
      },
      "checkConstraint": {}
    },
    "leak_sensors": {
      "name": "leak_sensors",
      "columns": {
        "id": {
          "name": "id",
          "type": "int",
          "primaryKey": false,
          "notNull": true,
          "autoincrement": true
        },
        "sensorUid": {
          "name": "sensorUid",
          "type": "varchar(64)",
          "primaryKey": false,
          "notNull": true,
          "autoincrement": false
        },
        "branchId": {
          "name": "branchId",
          "type": "int",
          "primaryKey": false,
          "notNull": false,
          "autoincrement": false
        },
        "customerName": {
          "name": "customerName",
          "type": "varchar(50)",
          "primaryKey": false,
          "notNull": true,
          "autoincrement": false
        },
        "phoneNumber": {
          "name": "phoneNumber",
          "type": "varchar(20)",
          "primaryKey": false,
          "notNull": true,
          "autoincrement": false
        },
        "apartmentName": {
          "name": "apartmentName",
          "type": "varchar(100)",
          "primaryKey": false,
          "notNull": true,
          "autoincrement": false
        },
        "dong": {
          "name": "dong",
          "type": "varchar(20)",
          "primaryKey": false,
          "notNull": true,
          "autoincrement": false
        },
        "ho": {
          "name": "ho",
          "type": "varchar(20)",
          "primaryKey": false,
          "notNull": true,
          "autoincrement": false
        },
        "sensorName": {
          "name": "sensorName",
          "type": "varchar(100)",
          "primaryKey": false,
          "notNull": true,
          "autoincrement": false
        },
        "installLocation": {
          "name": "installLocation",
          "type": "varchar(100)",
          "primaryKey": false,
          "notNull": true,
          "autoincrement": false
        },
        "status": {
          "name": "status",
          "type": "enum('정상','누수감지','배터리부족','통신끊김','점검필요')",
          "primaryKey": false,
          "notNull": true,
          "autoincrement": false,
          "default": "'정상'"
        },
        "batteryLevel": {
          "name": "batteryLevel",
          "type": "int",
          "primaryKey": false,
          "notNull": true,
          "autoincrement": false,
          "default": 100
        },
        "lastCommAt": {
          "name": "lastCommAt",
          "type": "timestamp",
          "primaryKey": false,
          "notNull": true,
          "autoincrement": false,
          "default": "(now())"
        },
        "leakDetectedAt": {
          "name": "leakDetectedAt",
          "type": "timestamp",
          "primaryKey": false,
          "notNull": false,
          "autoincrement": false
        },
        "isResolved": {
          "name": "isResolved",
          "type": "boolean",
          "primaryKey": false,
          "notNull": true,
          "autoincrement": false,
          "default": true
        },
        "technicianId": {
          "name": "technicianId",
          "type": "int",
          "primaryKey": false,
          "notNull": false,
          "autoincrement": false
        },
        "technicianName": {
          "name": "technicianName",
          "type": "varchar(50)",
          "primaryKey": false,
          "notNull": false,
          "autoincrement": false
        },
        "adminMemo": {
          "name": "adminMemo",
          "type": "text",
          "primaryKey": false,
          "notNull": false,
          "autoincrement": false
        },
        "createdAt": {
          "name": "createdAt",
          "type": "timestamp",
          "primaryKey": false,
          "notNull": true,
          "autoincrement": false,
          "default": "(now())"
        },
        "updatedAt": {
          "name": "updatedAt",
          "type": "timestamp",
          "primaryKey": false,
          "notNull": true,
          "autoincrement": false,
          "onUpdate": true,
          "default": "(now())"
        }
      },
      "indexes": {},
      "foreignKeys": {},
      "compositePrimaryKeys": {
        "leak_sensors_id": {
          "name": "leak_sensors_id",
          "columns": [
            "id"
          ]
        }
      },
      "uniqueConstraints": {
        "leak_sensors_sensorUid_unique": {
          "name": "leak_sensors_sensorUid_unique",
          "columns": [
            "sensorUid"
          ]
        }
      },
      "checkConstraint": {}
    },
    "location_consents": {
      "name": "location_consents",
      "columns": {
        "id": {
          "name": "id",
          "type": "int",
          "primaryKey": false,
          "notNull": true,
          "autoincrement": true
        },
        "technicianId": {
          "name": "technicianId",
          "type": "int",
          "primaryKey": false,
          "notNull": true,
          "autoincrement": false
        },
        "consentedAt": {
          "name": "consentedAt",
          "type": "timestamp",
          "primaryKey": false,
          "notNull": true,
          "autoincrement": false,
          "default": "(now())"
        },
        "consentVersion": {
          "name": "consentVersion",
          "type": "varchar(10)",
          "primaryKey": false,
          "notNull": true,
          "autoincrement": false,
          "default": "'1.0'"
        },
        "isActive": {
          "name": "isActive",
          "type": "boolean",
          "primaryKey": false,
          "notNull": true,
          "autoincrement": false,
          "default": true
        }
      },
      "indexes": {},
      "foreignKeys": {},
      "compositePrimaryKeys": {
        "location_consents_id": {
          "name": "location_consents_id",
          "columns": [
            "id"
          ]
        }
      },
      "uniqueConstraints": {},
      "checkConstraint": {}
    },
    "location_sessions": {
      "name": "location_sessions",
      "columns": {
        "id": {
          "name": "id",
          "type": "int",
          "primaryKey": false,
          "notNull": true,
          "autoincrement": true
        },
        "requestId": {
          "name": "requestId",
          "type": "int",
          "primaryKey": false,
          "notNull": true,
          "autoincrement": false
        },
        "technicianId": {
          "name": "technicianId",
          "type": "int",
          "primaryKey": false,
          "notNull": true,
          "autoincrement": false
        },
        "technicianName": {
          "name": "technicianName",
          "type": "varchar(50)",
          "primaryKey": false,
          "notNull": false,
          "autoincrement": false
        },
        "technicianPhone": {
          "name": "technicianPhone",
          "type": "varchar(20)",
          "primaryKey": false,
          "notNull": false,
          "autoincrement": false
        },
        "customerName": {
          "name": "customerName",
          "type": "varchar(50)",
          "primaryKey": false,
          "notNull": false,
          "autoincrement": false
        },
        "customerPhone": {
          "name": "customerPhone",
          "type": "varchar(20)",
          "primaryKey": false,
          "notNull": false,
          "autoincrement": false
        },
        "customerAddress": {
          "name": "customerAddress",
          "type": "varchar(200)",
          "primaryKey": false,
          "notNull": false,
          "autoincrement": false
        },
        "customerLat": {
          "name": "customerLat",
          "type": "decimal(10,7)",
          "primaryKey": false,
          "notNull": false,
          "autoincrement": false
        },
        "customerLng": {
          "name": "customerLng",
          "type": "decimal(10,7)",
          "primaryKey": false,
          "notNull": false,
          "autoincrement": false
        },
        "branchId": {
          "name": "branchId",
          "type": "int",
          "primaryKey": false,
          "notNull": false,
          "autoincrement": false
        },
        "branchName": {
          "name": "branchName",
          "type": "varchar(100)",
          "primaryKey": false,
          "notNull": false,
          "autoincrement": false
        },
        "trackingToken": {
          "name": "trackingToken",
          "type": "varchar(64)",
          "primaryKey": false,
          "notNull": true,
          "autoincrement": false
        },
        "currentLat": {
          "name": "currentLat",
          "type": "decimal(10,7)",
          "primaryKey": false,
          "notNull": false,
          "autoincrement": false
        },
        "currentLng": {
          "name": "currentLng",
          "type": "decimal(10,7)",
          "primaryKey": false,
          "notNull": false,
          "autoincrement": false
        },
        "currentUpdatedAt": {
          "name": "currentUpdatedAt",
          "type": "timestamp",
          "primaryKey": false,
          "notNull": false,
          "autoincrement": false
        },
        "status": {
          "name": "status",
          "type": "enum('이동중','도착완료','업무취소','만료')",
          "primaryKey": false,
          "notNull": true,
          "autoincrement": false,
          "default": "'이동중'"
        },
        "departedAt": {
          "name": "departedAt",
          "type": "timestamp",
          "primaryKey": false,
          "notNull": true,
          "autoincrement": false,
          "default": "(now())"
        },
        "arrivedAt": {
          "name": "arrivedAt",
          "type": "timestamp",
          "primaryKey": false,
          "notNull": false,
          "autoincrement": false
        },
        "cancelledAt": {
          "name": "cancelledAt",
          "type": "timestamp",
          "primaryKey": false,
          "notNull": false,
          "autoincrement": false
        },
        "expiresAt": {
          "name": "expiresAt",
          "type": "timestamp",
          "primaryKey": false,
          "notNull": true,
          "autoincrement": false
        },
        "smsSentAt": {
          "name": "smsSentAt",
          "type": "timestamp",
          "primaryKey": false,
          "notNull": false,
          "autoincrement": false
        },
        "createdAt": {
          "name": "createdAt",
          "type": "timestamp",
          "primaryKey": false,
          "notNull": true,
          "autoincrement": false,
          "default": "(now())"
        },
        "updatedAt": {
          "name": "updatedAt",
          "type": "timestamp",
          "primaryKey": false,
          "notNull": true,
          "autoincrement": false,
          "onUpdate": true,
          "default": "(now())"
        }
      },
      "indexes": {},
      "foreignKeys": {},
      "compositePrimaryKeys": {
        "location_sessions_id": {
          "name": "location_sessions_id",
          "columns": [
            "id"
          ]
        }
      },
      "uniqueConstraints": {
        "location_sessions_trackingToken_unique": {
          "name": "location_sessions_trackingToken_unique",
          "columns": [
            "trackingToken"
          ]
        }
      },
      "checkConstraint": {}
    },
    "material_orders": {
      "name": "material_orders",
      "columns": {
        "id": {
          "name": "id",
          "type": "int",
          "primaryKey": false,
          "notNull": true,
          "autoincrement": true
        },
        "branchId": {
          "name": "branchId",
          "type": "int",
          "primaryKey": false,
          "notNull": true,
          "autoincrement": false
        },
        "orderItems": {
          "name": "orderItems",
          "type": "text",
          "primaryKey": false,
          "notNull": true,
          "autoincrement": false
        },
        "status": {
          "name": "status",
          "type": "enum('신청','승인','발송','완료','반려')",
          "primaryKey": false,
          "notNull": true,
          "autoincrement": false,
          "default": "'신청'"
        },
        "requestedBy": {
          "name": "requestedBy",
          "type": "int",
          "primaryKey": false,
          "notNull": true,
          "autoincrement": false
        },
        "approvedBy": {
          "name": "approvedBy",
          "type": "int",
          "primaryKey": false,
          "notNull": false,
          "autoincrement": false
        },
        "memo": {
          "name": "memo",
          "type": "text",
          "primaryKey": false,
          "notNull": false,
          "autoincrement": false
        },
        "createdAt": {
          "name": "createdAt",
          "type": "timestamp",
          "primaryKey": false,
          "notNull": true,
          "autoincrement": false,
          "default": "(now())"
        },
        "updatedAt": {
          "name": "updatedAt",
          "type": "timestamp",
          "primaryKey": false,
          "notNull": true,
          "autoincrement": false,
          "onUpdate": true,
          "default": "(now())"
        }
      },
      "indexes": {},
      "foreignKeys": {},
      "compositePrimaryKeys": {
        "material_orders_id": {
          "name": "material_orders_id",
          "columns": [
            "id"
          ]
        }
      },
      "uniqueConstraints": {},
      "checkConstraint": {}
    },
    "notices": {
      "name": "notices",
      "columns": {
        "id": {
          "name": "id",
          "type": "int",
          "primaryKey": false,
          "notNull": true,
          "autoincrement": true
        },
        "title": {
          "name": "title",
          "type": "varchar(200)",
          "primaryKey": false,
          "notNull": true,
          "autoincrement": false
        },
        "content": {
          "name": "content",
          "type": "text",
          "primaryKey": false,
          "notNull": true,
          "autoincrement": false
        },
        "authorId": {
          "name": "authorId",
          "type": "int",
          "primaryKey": false,
          "notNull": true,
          "autoincrement": false
        },
        "targetBranchId": {
          "name": "targetBranchId",
          "type": "int",
          "primaryKey": false,
          "notNull": false,
          "autoincrement": false
        },
        "isPinned": {
          "name": "isPinned",
          "type": "boolean",
          "primaryKey": false,
          "notNull": true,
          "autoincrement": false,
          "default": false
        },
        "createdAt": {
          "name": "createdAt",
          "type": "timestamp",
          "primaryKey": false,
          "notNull": true,
          "autoincrement": false,
          "default": "(now())"
        },
        "updatedAt": {
          "name": "updatedAt",
          "type": "timestamp",
          "primaryKey": false,
          "notNull": true,
          "autoincrement": false,
          "onUpdate": true,
          "default": "(now())"
        }
      },
      "indexes": {},
      "foreignKeys": {},
      "compositePrimaryKeys": {
        "notices_id": {
          "name": "notices_id",
          "columns": [
            "id"
          ]
        }
      },
      "uniqueConstraints": {},
      "checkConstraint": {}
    },
    "notification_logs": {
      "name": "notification_logs",
      "columns": {
        "id": {
          "name": "id",
          "type": "int",
          "primaryKey": false,
          "notNull": true,
          "autoincrement": true
        },
        "requestId": {
          "name": "requestId",
          "type": "int",
          "primaryKey": false,
          "notNull": false,
          "autoincrement": false
        },
        "phoneNumber": {
          "name": "phoneNumber",
          "type": "varchar(20)",
          "primaryKey": false,
          "notNull": true,
          "autoincrement": false
        },
        "channel": {
          "name": "channel",
          "type": "enum('SMS','ALIMTALK')",
          "primaryKey": false,
          "notNull": true,
          "autoincrement": false,
          "default": "'SMS'"
        },
        "messageType": {
          "name": "messageType",
          "type": "varchar(50)",
          "primaryKey": false,
          "notNull": false,
          "autoincrement": false
        },
        "content": {
          "name": "content",
          "type": "text",
          "primaryKey": false,
          "notNull": false,
          "autoincrement": false
        },
        "result": {
          "name": "result",
          "type": "enum('SUCCESS','FAILED','SKIPPED')",
          "primaryKey": false,
          "notNull": true,
          "autoincrement": false,
          "default": "'SKIPPED'"
        },
        "errorMessage": {
          "name": "errorMessage",
          "type": "text",
          "primaryKey": false,
          "notNull": false,
          "autoincrement": false
        },
        "createdAt": {
          "name": "createdAt",
          "type": "timestamp",
          "primaryKey": false,
          "notNull": true,
          "autoincrement": false,
          "default": "(now())"
        }
      },
      "indexes": {},
      "foreignKeys": {},
      "compositePrimaryKeys": {
        "notification_logs_id": {
          "name": "notification_logs_id",
          "columns": [
            "id"
          ]
        }
      },
      "uniqueConstraints": {},
      "checkConstraint": {}
    },
    "phone_verifications": {
      "name": "phone_verifications",
      "columns": {
        "id": {
          "name": "id",
          "type": "int",
          "primaryKey": false,
          "notNull": true,
          "autoincrement": true
        },
        "phoneNumber": {
          "name": "phoneNumber",
          "type": "varchar(20)",
          "primaryKey": false,
          "notNull": true,
          "autoincrement": false
        },
        "code": {
          "name": "code",
          "type": "varchar(6)",
          "primaryKey": false,
          "notNull": true,
          "autoincrement": false
        },
        "purpose": {
          "name": "purpose",
          "type": "varchar(20)",
          "primaryKey": false,
          "notNull": true,
          "autoincrement": false,
          "default": "'signup'"
        },
        "verified": {
          "name": "verified",
          "type": "boolean",
          "primaryKey": false,
          "notNull": true,
          "autoincrement": false,
          "default": false
        },
        "expiresAt": {
          "name": "expiresAt",
          "type": "timestamp",
          "primaryKey": false,
          "notNull": true,
          "autoincrement": false
        },
        "createdAt": {
          "name": "createdAt",
          "type": "timestamp",
          "primaryKey": false,
          "notNull": true,
          "autoincrement": false,
          "default": "(now())"
        }
      },
      "indexes": {},
      "foreignKeys": {},
      "compositePrimaryKeys": {
        "phone_verifications_id": {
          "name": "phone_verifications_id",
          "columns": [
            "id"
          ]
        }
      },
      "uniqueConstraints": {},
      "checkConstraint": {}
    },
    "region_mappings": {
      "name": "region_mappings",
      "columns": {
        "id": {
          "name": "id",
          "type": "int",
          "primaryKey": false,
          "notNull": true,
          "autoincrement": true
        },
        "branchId": {
          "name": "branchId",
          "type": "int",
          "primaryKey": false,
          "notNull": true,
          "autoincrement": false
        },
        "keyword": {
          "name": "keyword",
          "type": "varchar(100)",
          "primaryKey": false,
          "notNull": true,
          "autoincrement": false
        },
        "priority": {
          "name": "priority",
          "type": "int",
          "primaryKey": false,
          "notNull": true,
          "autoincrement": false,
          "default": 0
        },
        "createdAt": {
          "name": "createdAt",
          "type": "timestamp",
          "primaryKey": false,
          "notNull": true,
          "autoincrement": false,
          "default": "(now())"
        }
      },
      "indexes": {},
      "foreignKeys": {},
      "compositePrimaryKeys": {
        "region_mappings_id": {
          "name": "region_mappings_id",
          "columns": [
            "id"
          ]
        }
      },
      "uniqueConstraints": {},
      "checkConstraint": {}
    },
    "repair_requests": {
      "name": "repair_requests",
      "columns": {
        "id": {
          "name": "id",
          "type": "int",
          "primaryKey": false,
          "notNull": true,
          "autoincrement": true
        },
        "requestNumber": {
          "name": "requestNumber",
          "type": "varchar(30)",
          "primaryKey": false,
          "notNull": true,
          "autoincrement": false
        },
        "branchId": {
          "name": "branchId",
          "type": "int",
          "primaryKey": false,
          "notNull": false,
          "autoincrement": false
        },
        "customerName": {
          "name": "customerName",
          "type": "varchar(50)",
          "primaryKey": false,
          "notNull": true,
          "autoincrement": false
        },
        "phoneNumber": {
          "name": "phoneNumber",
          "type": "varchar(20)",
          "primaryKey": false,
          "notNull": true,
          "autoincrement": false
        },
        "apartmentName": {
          "name": "apartmentName",
          "type": "varchar(100)",
          "primaryKey": false,
          "notNull": true,
          "autoincrement": false
        },
        "dong": {
          "name": "dong",
          "type": "varchar(20)",
          "primaryKey": false,
          "notNull": true,
          "autoincrement": false
        },
        "ho": {
          "name": "ho",
          "type": "varchar(20)",
          "primaryKey": false,
          "notNull": true,
          "autoincrement": false
        },
        "requestType": {
          "name": "requestType",
          "type": "enum('난방고장','배관청소')",
          "primaryKey": false,
          "notNull": true,
          "autoincrement": false,
          "default": "'난방고장'"
        },
        "symptom": {
          "name": "symptom",
          "type": "enum('집전체가춥다','방일부만춥다','분배기에서물이샌다','온도조절기가작동하지않는다','난방비가많이나온다','배관청소가필요하다','기타문의')",
          "primaryKey": false,
          "notNull": true,
          "autoincrement": false
        },
        "symptoms": {
          "name": "symptoms",
          "type": "text",
          "primaryKey": false,
          "notNull": false,
          "autoincrement": false
        },
        "detailContent": {
          "name": "detailContent",
          "type": "text",
          "primaryKey": false,
          "notNull": false,
          "autoincrement": false
        },
        "photoUrl": {
          "name": "photoUrl",
          "type": "text",
          "primaryKey": false,
          "notNull": false,
          "autoincrement": false
        },
        "preferredDate": {
          "name": "preferredDate",
          "type": "varchar(20)",
          "primaryKey": false,
          "notNull": false,
          "autoincrement": false
        },
        "preferredTime": {
          "name": "preferredTime",
          "type": "varchar(20)",
          "primaryKey": false,
          "notNull": false,
          "autoincrement": false
        },
        "status": {
          "name": "status",
          "type": "enum('신규접수','기사배정대기','방문예정','작업진행중','견적승인대기','작업완료','재방문필요')",
          "primaryKey": false,
          "notNull": true,
          "autoincrement": false,
          "default": "'신규접수'"
        },
        "technicianId": {
          "name": "technicianId",
          "type": "int",
          "primaryKey": false,
          "notNull": false,
          "autoincrement": false
        },
        "technicianName": {
          "name": "technicianName",
          "type": "varchar(50)",
          "primaryKey": false,
          "notNull": false,
          "autoincrement": false
        },
        "scheduledDate": {
          "name": "scheduledDate",
          "type": "varchar(20)",
          "primaryKey": false,
          "notNull": false,
          "autoincrement": false
        },
        "scheduledTime": {
          "name": "scheduledTime",
          "type": "varchar(20)",
          "primaryKey": false,
          "notNull": false,
          "autoincrement": false
        },
        "adminMemo": {
          "name": "adminMemo",
          "type": "text",
          "primaryKey": false,
          "notNull": false,
          "autoincrement": false
        },
        "inspectionResult": {
          "name": "inspectionResult",
          "type": "text",
          "primaryKey": false,
          "notNull": false,
          "autoincrement": false
        },
        "estimateAmount": {
          "name": "estimateAmount",
          "type": "decimal(12,2)",
          "primaryKey": false,
          "notNull": false,
          "autoincrement": false
        },
        "estimateSentAt": {
          "name": "estimateSentAt",
          "type": "timestamp",
          "primaryKey": false,
          "notNull": false,
          "autoincrement": false
        },
        "estimateApprovedAt": {
          "name": "estimateApprovedAt",
          "type": "timestamp",
          "primaryKey": false,
          "notNull": false,
          "autoincrement": false
        },
        "workflowStage": {
          "name": "workflowStage",
          "type": "enum('접수완료','지사배정','현장확인','견적작성','견적전달','견적승인','기사배정','일정확정','기사출발','기사도착','작업진행','작업완료','결제완료','후기요청')",
          "primaryKey": false,
          "notNull": true,
          "autoincrement": false,
          "default": "'접수완료'"
        },
        "paidAt": {
          "name": "paidAt",
          "type": "timestamp",
          "primaryKey": false,
          "notNull": false,
          "autoincrement": false
        },
        "reviewRequestedAt": {
          "name": "reviewRequestedAt",
          "type": "timestamp",
          "primaryKey": false,
          "notNull": false,
          "autoincrement": false
        },
        "scheduleChangeReason": {
          "name": "scheduleChangeReason",
          "type": "text",
          "primaryKey": false,
          "notNull": false,
          "autoincrement": false
        },
        "completedAt": {
          "name": "completedAt",
          "type": "timestamp",
          "primaryKey": false,
          "notNull": false,
          "autoincrement": false
        },
        "completionMemo": {
          "name": "completionMemo",
          "type": "text",
          "primaryKey": false,
          "notNull": false,
          "autoincrement": false
        },
        "isUrgent": {
          "name": "isUrgent",
          "type": "boolean",
          "primaryKey": false,
          "notNull": true,
          "autoincrement": false,
          "default": false
        },
        "needsRevisit": {
          "name": "needsRevisit",
          "type": "boolean",
          "primaryKey": false,
          "notNull": true,
          "autoincrement": false,
          "default": false
        },
        "revisitReason": {
          "name": "revisitReason",
          "type": "text",
          "primaryKey": false,
          "notNull": false,
          "autoincrement": false
        },
        "createdAt": {
          "name": "createdAt",
          "type": "timestamp",
          "primaryKey": false,
          "notNull": true,
          "autoincrement": false,
          "default": "(now())"
        },
        "updatedAt": {
          "name": "updatedAt",
          "type": "timestamp",
          "primaryKey": false,
          "notNull": true,
          "autoincrement": false,
          "onUpdate": true,
          "default": "(now())"
        }
      },
      "indexes": {},
      "foreignKeys": {},
      "compositePrimaryKeys": {
        "repair_requests_id": {
          "name": "repair_requests_id",
          "columns": [
            "id"
          ]
        }
      },
      "uniqueConstraints": {
        "repair_requests_requestNumber_unique": {
          "name": "repair_requests_requestNumber_unique",
          "columns": [
            "requestNumber"
          ]
        }
      },
      "checkConstraint": {}
    },
    "sensor_events": {
      "name": "sensor_events",
      "columns": {
        "id": {
          "name": "id",
          "type": "int",
          "primaryKey": false,
          "notNull": true,
          "autoincrement": true
        },
        "sensorUid": {
          "name": "sensorUid",
          "type": "varchar(64)",
          "primaryKey": false,
          "notNull": true,
          "autoincrement": false
        },
        "leakDetected": {
          "name": "leakDetected",
          "type": "boolean",
          "primaryKey": false,
          "notNull": true,
          "autoincrement": false,
          "default": false
        },
        "batteryLevel": {
          "name": "batteryLevel",
          "type": "int",
          "primaryKey": false,
          "notNull": false,
          "autoincrement": false
        },
        "reportedAt": {
          "name": "reportedAt",
          "type": "timestamp",
          "primaryKey": false,
          "notNull": true,
          "autoincrement": false,
          "default": "(now())"
        },
        "source": {
          "name": "source",
          "type": "enum('DEMO_TEST','WEBHOOK')",
          "primaryKey": false,
          "notNull": true,
          "autoincrement": false,
          "default": "'WEBHOOK'"
        },
        "rawPayload": {
          "name": "rawPayload",
          "type": "text",
          "primaryKey": false,
          "notNull": false,
          "autoincrement": false
        },
        "createdAt": {
          "name": "createdAt",
          "type": "timestamp",
          "primaryKey": false,
          "notNull": true,
          "autoincrement": false,
          "default": "(now())"
        }
      },
      "indexes": {},
      "foreignKeys": {},
      "compositePrimaryKeys": {
        "sensor_events_id": {
          "name": "sensor_events_id",
          "columns": [
            "id"
          ]
        }
      },
      "uniqueConstraints": {},
      "checkConstraint": {}
    },
    "technicians": {
      "name": "technicians",
      "columns": {
        "id": {
          "name": "id",
          "type": "int",
          "primaryKey": false,
          "notNull": true,
          "autoincrement": true
        },
        "name": {
          "name": "name",
          "type": "varchar(50)",
          "primaryKey": false,
          "notNull": true,
          "autoincrement": false
        },
        "phoneNumber": {
          "name": "phoneNumber",
          "type": "varchar(20)",
          "primaryKey": false,
          "notNull": false,
          "autoincrement": false
        },
        "specialty": {
          "name": "specialty",
          "type": "varchar(100)",
          "primaryKey": false,
          "notNull": false,
          "autoincrement": false
        },
        "branchId": {
          "name": "branchId",
          "type": "int",
          "primaryKey": false,
          "notNull": false,
          "autoincrement": false
        },
        "userId": {
          "name": "userId",
          "type": "int",
          "primaryKey": false,
          "notNull": false,
          "autoincrement": false
        },
        "isActive": {
          "name": "isActive",
          "type": "boolean",
          "primaryKey": false,
          "notNull": true,
          "autoincrement": false,
          "default": true
        },
        "createdAt": {
          "name": "createdAt",
          "type": "timestamp",
          "primaryKey": false,
          "notNull": true,
          "autoincrement": false,
          "default": "(now())"
        }
      },
      "indexes": {},
      "foreignKeys": {},
      "compositePrimaryKeys": {
        "technicians_id": {
          "name": "technicians_id",
          "columns": [
            "id"
          ]
        }
      },
      "uniqueConstraints": {},
      "checkConstraint": {}
    },
    "training_materials": {
      "name": "training_materials",
      "columns": {
        "id": {
          "name": "id",
          "type": "int",
          "primaryKey": false,
          "notNull": true,
          "autoincrement": true
        },
        "title": {
          "name": "title",
          "type": "varchar(200)",
          "primaryKey": false,
          "notNull": true,
          "autoincrement": false
        },
        "content": {
          "name": "content",
          "type": "text",
          "primaryKey": false,
          "notNull": false,
          "autoincrement": false
        },
        "fileUrl": {
          "name": "fileUrl",
          "type": "text",
          "primaryKey": false,
          "notNull": false,
          "autoincrement": false
        },
        "category": {
          "name": "category",
          "type": "varchar(50)",
          "primaryKey": false,
          "notNull": false,
          "autoincrement": false
        },
        "authorId": {
          "name": "authorId",
          "type": "int",
          "primaryKey": false,
          "notNull": true,
          "autoincrement": false
        },
        "createdAt": {
          "name": "createdAt",
          "type": "timestamp",
          "primaryKey": false,
          "notNull": true,
          "autoincrement": false,
          "default": "(now())"
        },
        "updatedAt": {
          "name": "updatedAt",
          "type": "timestamp",
          "primaryKey": false,
          "notNull": true,
          "autoincrement": false,
          "onUpdate": true,
          "default": "(now())"
        }
      },
      "indexes": {},
      "foreignKeys": {},
      "compositePrimaryKeys": {
        "training_materials_id": {
          "name": "training_materials_id",
          "columns": [
            "id"
          ]
        }
      },
      "uniqueConstraints": {},
      "checkConstraint": {}
    },
    "users": {
      "name": "users",
      "columns": {
        "id": {
          "name": "id",
          "type": "int",
          "primaryKey": false,
          "notNull": true,
          "autoincrement": true
        },
        "openId": {
          "name": "openId",
          "type": "varchar(64)",
          "primaryKey": false,
          "notNull": true,
          "autoincrement": false
        },
        "name": {
          "name": "name",
          "type": "text",
          "primaryKey": false,
          "notNull": false,
          "autoincrement": false
        },
        "email": {
          "name": "email",
          "type": "varchar(320)",
          "primaryKey": false,
          "notNull": false,
          "autoincrement": false
        },
        "loginMethod": {
          "name": "loginMethod",
          "type": "varchar(64)",
          "primaryKey": false,
          "notNull": false,
          "autoincrement": false
        },
        "role": {
          "name": "role",
          "type": "enum('user','admin')",
          "primaryKey": false,
          "notNull": true,
          "autoincrement": false,
          "default": "'user'"
        },
        "createdAt": {
          "name": "createdAt",
          "type": "timestamp",
          "primaryKey": false,
          "notNull": true,
          "autoincrement": false,
          "default": "(now())"
        },
        "updatedAt": {
          "name": "updatedAt",
          "type": "timestamp",
          "primaryKey": false,
          "notNull": true,
          "autoincrement": false,
          "onUpdate": true,
          "default": "(now())"
        },
        "lastSignedIn": {
          "name": "lastSignedIn",
          "type": "timestamp",
          "primaryKey": false,
          "notNull": true,
          "autoincrement": false,
          "default": "(now())"
        }
      },
      "indexes": {},
      "foreignKeys": {},
      "compositePrimaryKeys": {
        "users_id": {
          "name": "users_id",
          "columns": [
            "id"
          ]
        }
      },
      "uniqueConstraints": {
        "users_openId_unique": {
          "name": "users_openId_unique",
          "columns": [
            "openId"
          ]
        }
      },
      "checkConstraint": {}
    },
    "work_reports": {
      "name": "work_reports",
      "columns": {
        "id": {
          "name": "id",
          "type": "int",
          "primaryKey": false,
          "notNull": true,
          "autoincrement": true
        },
        "requestId": {
          "name": "requestId",
          "type": "int",
          "primaryKey": false,
          "notNull": true,
          "autoincrement": false
        },
        "technicianId": {
          "name": "technicianId",
          "type": "int",
          "primaryKey": false,
          "notNull": true,
          "autoincrement": false
        },
        "checkItems": {
          "name": "checkItems",
          "type": "text",
          "primaryKey": false,
          "notNull": false,
          "autoincrement": false
        },
        "usedMaterials": {
          "name": "usedMaterials",
          "type": "text",
          "primaryKey": false,
          "notNull": false,
          "autoincrement": false
        },
        "beforePhotoUrl": {
          "name": "beforePhotoUrl",
          "type": "text",
          "primaryKey": false,
          "notNull": false,
          "autoincrement": false
        },
        "afterPhotoUrl": {
          "name": "afterPhotoUrl",
          "type": "text",
          "primaryKey": false,
          "notNull": false,
          "autoincrement": false
        },
        "customerSignatureUrl": {
          "name": "customerSignatureUrl",
          "type": "text",
          "primaryKey": false,
          "notNull": false,
          "autoincrement": false
        },
        "workMemo": {
          "name": "workMemo",
          "type": "text",
          "primaryKey": false,
          "notNull": false,
          "autoincrement": false
        },
        "isCompleted": {
          "name": "isCompleted",
          "type": "boolean",
          "primaryKey": false,
          "notNull": true,
          "autoincrement": false,
          "default": false
        },
        "completedAt": {
          "name": "completedAt",
          "type": "timestamp",
          "primaryKey": false,
          "notNull": false,
          "autoincrement": false
        },
        "createdAt": {
          "name": "createdAt",
          "type": "timestamp",
          "primaryKey": false,
          "notNull": true,
          "autoincrement": false,
          "default": "(now())"
        },
        "updatedAt": {
          "name": "updatedAt",
          "type": "timestamp",
          "primaryKey": false,
          "notNull": true,
          "autoincrement": false,
          "onUpdate": true,
          "default": "(now())"
        }
      },
      "indexes": {},
      "foreignKeys": {},
      "compositePrimaryKeys": {
        "work_reports_id": {
          "name": "work_reports_id",
          "columns": [
            "id"
          ]
        }
      },
      "uniqueConstraints": {},
      "checkConstraint": {}
    }
  },
  "views": {},
  "_meta": {
    "schemas": {},
    "tables": {},
    "columns": {}
  },
  "internal": {
    "tables": {},
    "indexes": {}
  }
}